<?xml version="1.0" encoding="utf-8"?><input_polylines><Polyline><point><x>-410.774036658127</x><y>-1882.42298103148</y><z>111.404481860205</z></point><point><x>58.4054666632728</x><y>-1451.51812524528</y><z>-12.4133752048801</z></point></Polyline><Polyline><point><x>-841.026449339028</x><y>-1883.02665782617</y><z>155.710590268027</z></point><point><x>-357.73344902751</x><y>-1452.32821241375</y><z>101.624664854593</z></point></Polyline><Polyline><point><x>-410.774036658127</x><y>-1282.4222446989</y><z>111.404481860205</z></point><point><x>58.4054666632728</x><y>-851.517388912705</y><z>-12.4133752048801</z></point></Polyline><Polyline><point><x>-839.774464083472</x><y>-1582.08009082232</y><z>155.268954031344</z></point><point><x>-357.459684167086</x><y>-1151.17523503646</y><z>102.045640158496</z></point></Polyline><Polyline><point><x>-841.026449339028</x><y>-1283.02592149359</y><z>155.710590268027</z></point><point><x>-357.73344902751</x><y>-852.327476081171</y><z>101.624664854593</z></point></Polyline><Polyline><point><x>-1271.85447328338</x><y>-1582.68376761669</y><z>135.595735947179</z></point><point><x>-785.871369580986</x><y>-1151.98532220462</y><z>153.423646481533</z></point></Polyline><Polyline><point><x>-840.157054111303</x><y>-982.421222442362</y><z>155.311770160886</z></point><point><x>-357.842274194918</x><y>-551.5163666565</y><z>102.088456288038</z></point></Polyline><Polyline><point><x>-1271.34027420687</x><y>-1281.16231289073</y><z>135.411238636465</z></point><point><x>-786.444508402972</x><y>-850.257457104768</y><z>153.751477750237</z></point></Polyline><Polyline><point><x>-1272.23706331122</x><y>-983.024899236736</y><z>135.638552076722</z></point><point><x>-786.253959608817</x><y>-552.326453824667</y><z>153.466462611075</z></point></Polyline><Polyline><point><x>-1695.81984894996</x><y>-1281.76598968521</y><z>52.3614915814687</z></point><point><x>-1217.75256715959</x><y>-851.067544273029</y><z>141.51913600805</z></point></Polyline><Polyline><point><x>-1271.7228642347</x><y>-681.503444510775</y><z>135.454054766007</z></point><point><x>-786.827098430804</x><y>-250.598588724811</y><z>153.794293879779</z></point></Polyline><Polyline><point><x>-1696.20243897779</x><y>-682.107121305251</y><z>52.4043077110109</z></point><point><x>-1218.13515718743</x><y>-251.408675893073</y><z>141.561952137592</z></point></Polyline><Polyline><point><x>-942.293760960433</x><y>-784.006493696859</y><z>185.911530727626</z></point><point><x>-1553.56408167215</x><y>-447.672042273335</y><z>118.598338463921</z></point></Polyline><Polyline><point><x>-942.293760955664</x><y>-1384.00513781273</y><z>185.911530729878</z></point><point><x>-1553.56408166739</x><y>-1047.6706863892</y><z>118.598338466173</z></point></Polyline><Polyline><point><x>-942.293760973428</x><y>-1084.00581579621</y><z>185.911530674351</z></point><point><x>-1553.5640816898</x><y>-747.671364374154</y><z>118.598338445566</z></point></Polyline><Polyline><point><x>-942.293760978168</x><y>-484.007171680366</y><z>185.911530672093</z></point><point><x>-1553.56408169454</x><y>-147.672720258307</y><z>118.598338443308</z></point></Polyline><Polyline><point><x>-506.727658398022</x><y>-1084.76293370578</y><z>156.995555091698</z></point><point><x>-1121.27996134943</x><y>-748.428482282622</y><z>179.533029952754</z></point></Polyline><Polyline><point><x>-506.727658392594</x><y>-1684.76157782165</y><z>156.995555093849</z></point><point><x>-1121.279961344</x><y>-1348.42712639849</y><z>179.533029954906</z></point></Polyline><Polyline><point><x>-506.727658418455</x><y>-1384.76225580513</y><z>156.995555041197</z></point><point><x>-1121.27996136937</x><y>-1048.42780438344</y><z>179.533029937478</z></point></Polyline><Polyline><point><x>-506.727658423856</x><y>-784.763611689285</y><z>156.995555039035</z></point><point><x>-1121.27996137477</x><y>-448.429160267594</y><z>179.533029935316</z></point></Polyline><Polyline><point><x>-80.0331489842765</x><y>-1385.51937371551</y><z>64.8773756815577</z></point><point><x>-684.730950543345</x><y>-1049.1849222913</y><z>176.783763456829</z></point></Polyline><Polyline><point><x>-80.033148979518</x><y>-1985.51801783138</y><z>64.8773756835478</z></point><point><x>-684.730950538586</x><y>-1649.18356640717</y><z>176.783763458819</z></point></Polyline><Polyline><point><x>-80.0331490123182</x><y>-1685.51869581487</y><z>64.8773756349027</z></point><point><x>-684.730950565765</x><y>-1349.18424439212</y><z>176.783763444951</z></point></Polyline><Polyline><point><x>-80.0331490170513</x><y>-1085.52005169902</y><z>64.8773756328981</z></point><point><x>-684.730950570498</x><y>-749.185600276275</y><z>176.783763442947</z></point></Polyline></input_polylines>